bs_cli/__init__.py
bs_cli/cli.py
bs_cli/commands/__init__.py
bs_cli/commands/create.py
bs_cli/commands/init.py
bs_cli/commands/migrate.py
bs_cli/commands/start.py
bs_cli/templates/__init__.py
bs_cli/templates/connection_template.py
bs_cli/templates/main_template.py
bs_cli/templates/model_template.py
bs_cli/templates/orm_template.py
bs_cli/templates/router_template.py
bs_cli/templates/schema_template.py
bs_cli/templates/security_template.py
bs_cli/utils/__init__.py
bs_cli/utils/file_manager.py
bs_cli/utils/template_renderer.py
base_system_api-0.1.1.dist-info/METADATA
base_system_api-0.1.1.dist-info/WHEEL
base_system_api-0.1.1.dist-info/entry_points.txt
base_system_api-0.1.1.dist-info/top_level.txt
base_system_api-0.1.1.dist-info/RECORD
