Metadata-Version: 2.4
Name: base-system-api
Version: 0.1.1
Summary: A CLI tool for generating FastAPI project structures and code
Home-page: https://github.com/seuusuario/fastapi-cli-bs
Author: Raian Barbosa
Author-email: BS CLI Developer <developer@example.com>
Classifier: Development Status :: 3 - Alpha
Classifier: Intended Audience :: Developers
Classifier: License :: OSI Approved :: MIT License
Classifier: Operating System :: OS Independent
Classifier: Programming Language :: Python :: 3
Classifier: Programming Language :: Python :: 3.8
Classifier: Programming Language :: Python :: 3.9
Classifier: Programming Language :: Python :: 3.10
Classifier: Programming Language :: Python :: 3.11
Requires-Python: >=3.7
Requires-Dist: click>=8.0.0
Requires-Dist: jinja2>=3.0.0
Dynamic: author
Dynamic: home-page
Dynamic: requires-python
